schema_description_agent/__init__.py
schema_description_agent/agent.py
schema_description_agent/config.py
schema_description_agent/constants.py
schema_description_agent/models.py
schema_description_agent-0.1.4.dist-info/METADATA
schema_description_agent-0.1.4.dist-info/WHEEL
schema_description_agent-0.1.4.dist-info/top_level.txt
schema_description_agent-0.1.4.dist-info/RECORD
