Metadata-Version: 2.4
Name: schema_description_agent
Version: 0.1.4
Summary: LLM-driven agent for describing data tables based on domain schemas
Author-email: StepFn AI <rajesh@stepfunction.ai>
License: MIT
Project-URL: Homepage, https://github.com/stepfnAI/table-description-agent
Project-URL: Repository, https://github.com/stepfnAI/table-description-agent
Project-URL: Issues, https://github.com/stepfnAI/table-description-agent/issues
Classifier: Development Status :: 3 - Alpha
Classifier: Intended Audience :: Developers
Classifier: Intended Audience :: Science/Research
Classifier: License :: OSI Approved :: MIT License
Classifier: Programming Language :: Python :: 3
Classifier: Programming Language :: Python :: 3.9
Classifier: Programming Language :: Python :: 3.10
Classifier: Programming Language :: Python :: 3.11
Classifier: Topic :: Scientific/Engineering :: Artificial Intelligence
Classifier: Topic :: Scientific/Engineering :: Information Analysis
Requires-Python: >=3.11
Requires-Dist: sfn-blueprint==0.7.4
Requires-Dist: pydantic-settings
Provides-Extra: dev
Requires-Dist: pytest>=7.0.0; extra == "dev"
Requires-Dist: pytest-cov>=4.0.0; extra == "dev"
Requires-Dist: black>=23.0.0; extra == "dev"
Requires-Dist: flake8>=6.0.0; extra == "dev"
Requires-Dist: mypy>=1.0.0; extra == "dev"
Requires-Dist: pytest-cov; extra == "dev"
